request_tester/__init__.py
request_tester/__main__.py
request_tester-0.18.dist-info/LICENSE
request_tester-0.18.dist-info/WHEEL
request_tester-0.18.dist-info/METADATA
request_tester-0.18.dist-info/RECORD
