Metadata-Version: 2.1
Name: request_tester
Version: 0.18
Summary: This is a simple HTTP interceptor. 
Author-email: nejdetckenobi <nejdetyucesoy@gmail.com>
Classifier: License :: OSI Approved :: GNU General Public License v3 or later (GPLv3+)
Project-URL: Home, https://github.com/nejdetckenobi/request_tester
